{
  "response": {
    "coarseTopics": [
      {
        "id": 0,
        "label": "Science",
        "wikiLink": "http://en.wikipedia.org/Category:Science",
        "score": 1
      },
      {
        "id": 1,
        "label": "Health",
        "wikiLink": "http://en.wikipedia.org/Category:Health",
        "score": 0.901858
      },
      {
        "id": 2,
        "label": "Business",
        "wikiLink": "http://en.wikipedia.org/Category:Business",
        "score": 0.794714
      },
      {
        "id": 3,
        "label": "Culture",
        "wikiLink": "http://en.wikipedia.org/Category:Culture",
        "score": 0.747685
      },
      {
        "id": 4,
        "label": "Mathematics",
        "wikiLink": "http://en.wikipedia.org/Category:Mathematics",
        "score": 0.674367
      },
      {
        "id": 5,
        "label": "Technology",
        "wikiLink": "http://en.wikipedia.org/Category:Technology",
        "score": 0.653198
      }
    ],
    "language": "eng",
    "languageIsReliable": true,
    "topics": [
      {
        "id": 0,
        "label": "Canada",
        "wikiLink": "http://en.wikipedia.org/Canada",
        "score": 0.110998
      },
      {
        "id": 1,
        "label": "Coronary artery disease",
        "wikiLink": "http://en.wikipedia.org/Coronary_artery_disease",
        "score": 0.456786
      },
      {
        "id": 2,
        "label": "Diabetes mellitus",
        "wikiLink": "http://en.wikipedia.org/Diabetes_mellitus",
        "score": 0.34334
      },
      {
        "id": 3,
        "label": "Equation",
        "wikiLink": "http://en.wikipedia.org/Equation",
        "score": 0.179306
      },
      {
        "id": 4,
        "label": "Evaluation",
        "wikiLink": "http://en.wikipedia.org/Evaluation",
        "score": 0.306042
      },
      {
        "id": 5,
        "label": "Framingham, Massachusetts",
        "wikiLink": "http://en.wikipedia.org/Framingham,_Massachusetts",
        "score": 0.169416
      },
      {
        "id": 6,
        "label": "Positive and negative predictive values",
        "wikiLink": "http://en.wikipedia.org/Positive_and_negative_predictive_values",
        "score": 0.342554
      },
      {
        "id": 7,
        "label": "Risk",
        "wikiLink": "http://en.wikipedia.org/Risk",
        "score": 1
      },
      {
        "id": 8,
        "label": "Sensitivity and specificity",
        "wikiLink": "http://en.wikipedia.org/Sensitivity_and_specificity",
        "score": 1
      },
      {
        "id": 9,
        "label": "Sheffield",
        "wikiLink": "http://en.wikipedia.org/Sheffield",
        "score": 0.104915
      },
      {
        "id": 10,
        "label": "Value (economics)",
        "wikiLink": "http://en.wikipedia.org/Value_(economics)",
        "score": 0.173604
      },
      {
        "id": 11,
        "label": "Fields of application of statistics",
        "wikiLink": "http://en.wikipedia.org/Category:Fields_of_application_of_statistics",
        "score": 0.505385
      },
      {
        "id": 12,
        "label": "Statistics",
        "wikiLink": "http://en.wikipedia.org/Category:Statistics",
        "score": 0.498701
      },
      {
        "id": 13,
        "label": "Applied mathematics",
        "wikiLink": "http://en.wikipedia.org/Category:Applied_mathematics",
        "score": 0.490436
      },
      {
        "id": 14,
        "label": "Geography",
        "wikiLink": "http://en.wikipedia.org/Category:Geography_by_country",
        "score": 0.302311
      },
      {
        "id": 15,
        "label": "Categorical data",
        "wikiLink": "http://en.wikipedia.org/Category:Categorical_data",
        "score": 0.194328
      },
      {
        "id": 16,
        "label": "Statistical data types",
        "wikiLink": "http://en.wikipedia.org/Category:Statistical_data_types",
        "score": 0.194328
      },
      {
        "id": 17,
        "label": "Summary statistics for contingency tables",
        "wikiLink": "http://en.wikipedia.org/Category:Summary_statistics_for_contingency_tables",
        "score": 0.193378
      },
      {
        "id": 18,
        "label": "Mathematical and theoretical biology",
        "wikiLink": "http://en.wikipedia.org/Category:Mathematical_and_theoretical_biology",
        "score": 0.193378
      },
      {
        "id": 19,
        "label": "Biostatistics",
        "wikiLink": "http://en.wikipedia.org/Category:Biostatistics",
        "score": 0.193378
      },
      {
        "id": 20,
        "label": "Systems biology",
        "wikiLink": "http://en.wikipedia.org/Category:Systems_biology",
        "score": 0.178429
      },
      {
        "id": 21,
        "label": "Ratios",
        "wikiLink": "http://en.wikipedia.org/Category:Ratios",
        "score": 0.172868
      },
      {
        "id": 22,
        "label": "Arithmetic",
        "wikiLink": "http://en.wikipedia.org/Category:Arithmetic",
        "score": 0.172868
      },
      {
        "id": 23,
        "label": "Statistical ratios",
        "wikiLink": "http://en.wikipedia.org/Category:Statistical_ratios",
        "score": 0.170707
      },
      {
        "id": 24,
        "label": "Scientific theories",
        "wikiLink": "http://en.wikipedia.org/Category:Scientific_theories",
        "score": 0.156141
      },
      {
        "id": 25,
        "label": "Value",
        "wikiLink": "http://en.wikipedia.org/Category:Value",
        "score": 0.0780795
      },
      {
        "id": 26,
        "label": "Social sciences",
        "wikiLink": "http://en.wikipedia.org/Category:Social_sciences",
        "score": 0.0780795
      },
      {
        "id": 27,
        "label": "Former empires",
        "wikiLink": "http://en.wikipedia.org/Category:Former_empires_by_continent",
        "score": 0.0391342
      },
      {
        "id": 28,
        "label": "Treaties",
        "wikiLink": "http://en.wikipedia.org/Category:Treaties_by_country",
        "score": 0.0391342
      },
      {
        "id": 29,
        "label": "Culture",
        "wikiLink": "http://en.wikipedia.org/Category:Culture_by_language",
        "score": 0.0391342
      },
      {
        "id": 30,
        "label": "Modern European colonies",
        "wikiLink": "http://en.wikipedia.org/Category:Modern_European_colonies",
        "score": 0.0391342
      },
      {
        "id": 31,
        "label": "British Overseas Territories and Crown Dependencies",
        "wikiLink": "http://en.wikipedia.org/Category:British_Overseas_Territories_and_Crown_Dependencies",
        "score": 0.0391342
      },
      {
        "id": 32,
        "label": "Former European colonies",
        "wikiLink": "http://en.wikipedia.org/Category:Former_European_colonies",
        "score": 0.0391342
      },
      {
        "id": 33,
        "label": "Monarchies",
        "wikiLink": "http://en.wikipedia.org/Category:Monarchies",
        "score": 0.0391342
      },
      {
        "id": 34,
        "label": "Dependent territories",
        "wikiLink": "http://en.wikipedia.org/Category:Dependent_territories_by_country",
        "score": 0.0391342
      },
      {
        "id": 35,
        "label": "Government",
        "wikiLink": "http://en.wikipedia.org/Category:Government_by_country",
        "score": 0.0391342
      },
      {
        "id": 36,
        "label": "Organizations",
        "wikiLink": "http://en.wikipedia.org/Category:Organizations_by_type",
        "score": 0.0391342
      },
      {
        "id": 37,
        "label": "Former colonies",
        "wikiLink": "http://en.wikipedia.org/Category:Former_colonies",
        "score": 0.0391342
      },
      {
        "id": 38,
        "label": "International relations",
        "wikiLink": "http://en.wikipedia.org/Category:International_relations",
        "score": 0.0391342
      },
      {
        "id": 39,
        "label": "Member states",
        "wikiLink": "http://en.wikipedia.org/Category:Member_states_by_organization",
        "score": 0.0391342
      },
      {
        "id": 40,
        "label": "English languages",
        "wikiLink": "http://en.wikipedia.org/Category:English_languages",
        "score": 0.0391342
      },
      {
        "id": 41,
        "label": "International organizations",
        "wikiLink": "http://en.wikipedia.org/Category:International_organizations",
        "score": 0.0391342
      },
      {
        "id": 42,
        "label": "Germanic languages",
        "wikiLink": "http://en.wikipedia.org/Category:Germanic_languages",
        "score": 0.0391342
      },
      {
        "id": 43,
        "label": "Monarchy",
        "wikiLink": "http://en.wikipedia.org/Category:Monarchy",
        "score": 0.0391342
      },
      {
        "id": 44,
        "label": "Cultural spheres of influence",
        "wikiLink": "http://en.wikipedia.org/Category:Cultural_spheres_of_influence",
        "score": 0.0391342
      },
      {
        "id": 45,
        "label": "Liberalism",
        "wikiLink": "http://en.wikipedia.org/Category:Liberalism",
        "score": 0.0391342
      },
      {
        "id": 46,
        "label": "Constitutional law",
        "wikiLink": "http://en.wikipedia.org/Category:Constitutional_law",
        "score": 0.0391342
      },
      {
        "id": 47,
        "label": "Constitutions",
        "wikiLink": "http://en.wikipedia.org/Category:Constitutions",
        "score": 0.0391342
      },
      {
        "id": 48,
        "label": "Overseas empires",
        "wikiLink": "http://en.wikipedia.org/Category:Overseas_empires",
        "score": 0.0391342
      },
      {
        "id": 49,
        "label": "British Empire",
        "wikiLink": "http://en.wikipedia.org/Category:British_Empire",
        "score": 0.0391342
      },
      {
        "id": 50,
        "label": "British nationalism",
        "wikiLink": "http://en.wikipedia.org/Category:British_nationalism",
        "score": 0.0391342
      },
      {
        "id": 51,
        "label": "English language",
        "wikiLink": "http://en.wikipedia.org/Category:English_language",
        "score": 0.0391342
      },
      {
        "id": 52,
        "label": "Democracy",
        "wikiLink": "http://en.wikipedia.org/Category:Democracy",
        "score": 0.0391342
      },
      {
        "id": 53,
        "label": "Political charters",
        "wikiLink": "http://en.wikipedia.org/Category:Political_charters",
        "score": 0.0391342
      },
      {
        "id": 54,
        "label": "Liberal democracies",
        "wikiLink": "http://en.wikipedia.org/Category:Liberal_democracies",
        "score": 0.0391342
      },
      {
        "id": 55,
        "label": "Constitutional monarchies",
        "wikiLink": "http://en.wikipedia.org/Category:Constitutional_monarchies",
        "score": 0.0391342
      },
      {
        "id": 56,
        "label": "Former British colonies",
        "wikiLink": "http://en.wikipedia.org/Category:Former_British_colonies",
        "score": 0.0391342
      }
    ],
    "entities": [
      {
        "id": 0,
        "matchingTokens": [
          2
        ],
        "entityId": "Evaluation",
        "freebaseTypes": [
          "/organization/organization_sector"
        ],
        "confidenceScore": 1.56555,
        "wikiLink": "http://en.wikipedia.org/wiki/Evaluation",
        "matchedText": "evaluation",
        "freebaseId": "/m/0gw5h",
        "relevanceScore": 0.306042,
        "entityEnglishId": "Evaluation",
        "startingPos": 9,
        "endingPos": 19
      },
      {
        "id": 1,
        "matchingTokens": [
          7
        ],
        "entityId": "Guideline",
        "confidenceScore": 1.14747,
        "wikiLink": "http://en.wikipedia.org/wiki/Guideline",
        "matchedText": "guidelines",
        "freebaseId": "/m/04xyb9",
        "relevanceScore": 0.0562251,
        "entityEnglishId": "Guideline",
        "startingPos": 42,
        "endingPos": 52
      },
      {
        "id": 2,
        "type": [
          "Place",
          "PopulatedPlace",
          "Settlement",
          "Town"
        ],
        "matchingTokens": [
          11
        ],
        "entityId": "Framingham, Massachusetts",
        "freebaseTypes": [
          "/location/dated_location",
          "/location/statistical_region",
          "/location/citytown",
          "/location/location"
        ],
        "confidenceScore": 2.03688,
        "wikiLink": "http://en.wikipedia.org/wiki/Framingham,_Massachusetts",
        "matchedText": "Framingham",
        "freebaseId": "/m/01m2n1",
        "relevanceScore": 0.0847079,
        "entityEnglishId": "Framingham, Massachusetts",
        "startingPos": 76,
        "endingPos": 86
      },
      {
        "id": 3,
        "matchingTokens": [
          12
        ],
        "entityId": "Equation",
        "confidenceScore": 1.7419,
        "wikiLink": "http://en.wikipedia.org/wiki/Equation",
        "matchedText": "equation",
        "freebaseId": "/m/02jnw",
        "relevanceScore": 0.179306,
        "entityEnglishId": "Equation",
        "startingPos": 87,
        "endingPos": 95
      },
      {
        "id": 4,
        "type": [
          "Disease"
        ],
        "matchingTokens": [
          17
        ],
        "entityId": "Diabetes mellitus",
        "freebaseTypes": [
          "/book/book_subject",
          "/medicine/disease_cause",
          "/organization/organization_sector",
          "/fictional_universe/medical_condition_in_fiction",
          "/people/cause_of_death",
          "/medicine/disease",
          "/medicine/risk_factor",
          "/film/film_subject",
          "/medicine/symptom",
          "/medicine/icd_9_cm_classification"
        ],
        "confidenceScore": 2.12115,
        "wikiLink": "http://en.wikipedia.org/wiki/Diabetes_mellitus",
        "matchedText": "diabetes",
        "freebaseId": "/m/0c58k",
        "relevanceScore": 0.34334,
        "entityEnglishId": "Diabetes mellitus",
        "startingPos": 115,
        "endingPos": 123
      },
      {
        "id": 5,
        "type": [
          "Place",
          "PopulatedPlace",
          "Settlement",
          "City"
        ],
        "matchingTokens": [
          21
        ],
        "entityId": "Sheffield",
        "freebaseTypes": [
          "/location/dated_location",
          "/government/governmental_jurisdiction",
          "/location/statistical_region",
          "/location/uk_statistical_location",
          "/location/uk_metropolitan_borough",
          "/location/citytown",
          "/travel/travel_destination",
          "/sports/sports_team_location",
          "/business/employer",
          "/location/location",
          "/periodicals/newspaper_circulation_area",
          "/location/administrative_division"
        ],
        "confidenceScore": 1.35495,
        "wikiLink": "http://en.wikipedia.org/wiki/Sheffield",
        "matchedText": "Sheffield",
        "freebaseId": "/m/0m75g",
        "relevanceScore": 0.104915,
        "entityEnglishId": "Sheffield",
        "startingPos": 142,
        "endingPos": 151
      },
      {
        "id": 6,
        "matchingTokens": [
          25
        ],
        "entityId": "Sensitivity and specificity",
        "confidenceScore": 1.63722,
        "wikiLink": "http://en.wikipedia.org/wiki/Sensitivity_and_specificity",
        "matchedText": "sensitivity",
        "freebaseId": "/m/047vmjj",
        "relevanceScore": 0.492979,
        "entityEnglishId": "Sensitivity and specificity",
        "startingPos": 171,
        "endingPos": 182
      },
      {
        "id": 7,
        "matchingTokens": [
          36
        ],
        "entityId": "Sensitivity and specificity",
        "confidenceScore": 2.09099,
        "wikiLink": "http://en.wikipedia.org/wiki/Sensitivity_and_specificity",
        "matchedText": "specificity",
        "freebaseId": "/m/047vmjj",
        "relevanceScore": 0.589608,
        "entityEnglishId": "Sensitivity and specificity",
        "startingPos": 223,
        "endingPos": 234
      },
      {
        "id": 8,
        "type": [
          "Place",
          "NaturalPlace",
          "MountainRange"
        ],
        "matchingTokens": [
          49
        ],
        "entityId": "Ith",
        "freebaseTypes": [
          "/location/location"
        ],
        "confidenceScore": 1.35231,
        "wikiLink": "http://en.wikipedia.org/wiki/Ith",
        "matchedText": "ith",
        "freebaseId": "/m/06wc7xw",
        "relevanceScore": 0.0205482,
        "entityEnglishId": "Ith",
        "startingPos": 285,
        "endingPos": 288
      },
      {
        "id": 9,
        "matchingTokens": [
          53,
          54,
          55
        ],
        "entityId": "Positive and negative predictive values",
        "confidenceScore": 5.44645,
        "wikiLink": "http://en.wikipedia.org/wiki/Positive_and_negative_predictive_values",
        "matchedText": "positive predictive value",
        "freebaseId": "/m/05b484",
        "relevanceScore": 0.342554,
        "entityEnglishId": "Positive and negative predictive values",
        "startingPos": 307,
        "endingPos": 332
      },
      {
        "id": 10,
        "matchingTokens": [
          55
        ],
        "entityId": "Value (economics)",
        "confidenceScore": 1.52765,
        "wikiLink": "http://en.wikipedia.org/wiki/Value_(economics)",
        "matchedText": "value",
        "freebaseId": "/m/0bhr4z",
        "relevanceScore": 0.173604,
        "entityEnglishId": "Value (economics)",
        "startingPos": 327,
        "endingPos": 332
      },
      {
        "id": 11,
        "type": [
          "Company"
        ],
        "matchingTokens": [
          67,
          68
        ],
        "entityId": "Joint Br",
        "freebaseTypes": [
          "/organization/organization"
        ],
        "confidenceScore": 0.5,
        "wikiLink": "",
        "matchedText": "Joint Br",
        "relevanceScore": 0,
        "entityEnglishId": "",
        "startingPos": 377,
        "endingPos": 385
      },
      {
        "id": 12,
        "matchingTokens": [
          73
        ],
        "entityId": "Sensitivity and specificity",
        "confidenceScore": 2.09099,
        "wikiLink": "http://en.wikipedia.org/wiki/Sensitivity_and_specificity",
        "matchedText": "specificity",
        "freebaseId": "/m/047vmjj",
        "relevanceScore": 0.589608,
        "entityEnglishId": "Sensitivity and specificity",
        "startingPos": 409,
        "endingPos": 420
      },
      {
        "id": 13,
        "matchingTokens": [
          81
        ],
        "entityId": "Sensitivity and specificity",
        "confidenceScore": 1.63722,
        "wikiLink": "http://en.wikipedia.org/wiki/Sensitivity_and_specificity",
        "matchedText": "sensitivity",
        "freebaseId": "/m/047vmjj",
        "relevanceScore": 0.492979,
        "entityEnglishId": "Sensitivity and specificity",
        "startingPos": 437,
        "endingPos": 448
      },
      {
        "id": 14,
        "type": [
          "Disease"
        ],
        "matchingTokens": [
          93
        ],
        "entityId": "Coronary artery disease",
        "freebaseTypes": [
          "/medicine/disease_cause",
          "/medicine/disease",
          "/medicine/risk_factor",
          "/people/cause_of_death"
        ],
        "confidenceScore": 1.44095,
        "wikiLink": "http://en.wikipedia.org/wiki/Coronary_artery_disease",
        "matchedText": "CHD",
        "freebaseId": "/m/01s1m",
        "relevanceScore": 0.456786,
        "entityEnglishId": "Coronary artery disease",
        "startingPos": 496,
        "endingPos": 499
      },
      {
        "id": 15,
        "matchingTokens": [
          94
        ],
        "entityId": "Risk",
        "freebaseTypes": [
          "/book/book_subject",
          "/media_common/quotation_subject"
        ],
        "confidenceScore": 0.968106,
        "wikiLink": "http://en.wikipedia.org/wiki/Risk",
        "matchedText": "risk",
        "freebaseId": "/m/06d5f",
        "relevanceScore": 0.295924,
        "entityEnglishId": "Risk",
        "startingPos": 500,
        "endingPos": 504
      },
      {
        "id": 16,
        "matchingTokens": [
          106
        ],
        "entityId": "Sensitivity and specificity",
        "confidenceScore": 2.09099,
        "wikiLink": "http://en.wikipedia.org/wiki/Sensitivity_and_specificity",
        "matchedText": "specificity",
        "freebaseId": "/m/047vmjj",
        "relevanceScore": 0.589608,
        "entityEnglishId": "Sensitivity and specificity",
        "startingPos": 552,
        "endingPos": 563
      },
      {
        "id": 17,
        "matchingTokens": [
          109
        ],
        "entityId": "Sensitivity and specificity",
        "confidenceScore": 1.63722,
        "wikiLink": "http://en.wikipedia.org/wiki/Sensitivity_and_specificity",
        "matchedText": "sensitivity",
        "freebaseId": "/m/047vmjj",
        "relevanceScore": 0.492979,
        "entityEnglishId": "Sensitivity and specificity",
        "startingPos": 569,
        "endingPos": 580
      },
      {
        "id": 18,
        "type": [
          "Place",
          "PopulatedPlace",
          "Country"
        ],
        "matchingTokens": [
          113
        ],
        "entityId": "Canada",
        "freebaseTypes": [
          "/law/court_jurisdiction_area",
          "/sports/sports_team_location",
          "/royalty/kingdom",
          "/periodicals/newspaper_circulation_area",
          "/film/film_location",
          "/exhibitions/exhibition_sponsor",
          "/organization/organization_member",
          "/military/military_combatant",
          "/cvg/computer_game_region",
          "/fictional_universe/fictional_setting",
          "/location/dated_location",
          "/olympics/olympic_participating_country",
          "/organization/organization_founder",
          "/tv/tv_location",
          "/sports/sport_country",
          "/business/employer",
          "/book/book_subject",
          "/food/beer_country_region",
          "/location/statistical_region",
          "/biology/breed_origin",
          "/location/country",
          "/symbols/flag_referent",
          "/film/film_subject",
          "/government/governmental_jurisdiction",
          "/symbols/coat_of_arms_bearer",
          "/location/administrative_division",
          "/organization/organization_scope",
          "/location/location"
        ],
        "confidenceScore": 2.07996,
        "wikiLink": "http://en.wikipedia.org/wiki/Canada",
        "matchedText": "Canadian",
        "freebaseId": "/m/0d060g",
        "relevanceScore": 0.110998,
        "entityEnglishId": "Canada",
        "startingPos": 587,
        "endingPos": 595
      },
      {
        "id": 19,
        "matchingTokens": [
          121
        ],
        "entityId": "Risk",
        "freebaseTypes": [
          "/book/book_subject",
          "/media_common/quotation_subject"
        ],
        "confidenceScore": 1.35772,
        "wikiLink": "http://en.wikipedia.org/wiki/Risk",
        "matchedText": "risk",
        "freebaseId": "/m/06d5f",
        "relevanceScore": 0.295924,
        "entityEnglishId": "Risk",
        "startingPos": 631,
        "endingPos": 635
      },
      {
        "id": 20,
        "matchingTokens": [
          137
        ],
        "entityId": "Risk",
        "freebaseTypes": [
          "/book/book_subject",
          "/media_common/quotation_subject"
        ],
        "confidenceScore": 1.35772,
        "wikiLink": "http://en.wikipedia.org/wiki/Risk",
        "matchedText": "risk",
        "freebaseId": "/m/06d5f",
        "relevanceScore": 0.295924,
        "entityEnglishId": "Risk",
        "startingPos": 707,
        "endingPos": 711
      },
      {
        "id": 21,
        "matchingTokens": [
          139
        ],
        "entityId": "Sensitivity and specificity",
        "confidenceScore": 2.09099,
        "wikiLink": "http://en.wikipedia.org/wiki/Sensitivity_and_specificity",
        "matchedText": "specificity",
        "freebaseId": "/m/047vmjj",
        "relevanceScore": 0.589608,
        "entityEnglishId": "Sensitivity and specificity",
        "startingPos": 713,
        "endingPos": 724
      },
      {
        "id": 22,
        "matchingTokens": [
          142
        ],
        "entityId": "Sensitivity and specificity",
        "confidenceScore": 1.63722,
        "wikiLink": "http://en.wikipedia.org/wiki/Sensitivity_and_specificity",
        "matchedText": "sensitivity",
        "freebaseId": "/m/047vmjj",
        "relevanceScore": 0.492979,
        "entityEnglishId": "Sensitivity and specificity",
        "startingPos": 731,
        "endingPos": 742
      },
      {
        "id": 23,
        "type": [
          "Place",
          "PopulatedPlace",
          "Settlement",
          "Town"
        ],
        "matchingTokens": [
          155
        ],
        "entityId": "Framingham, Massachusetts",
        "freebaseTypes": [
          "/location/dated_location",
          "/location/statistical_region",
          "/location/citytown",
          "/location/location"
        ],
        "confidenceScore": 2.03688,
        "wikiLink": "http://en.wikipedia.org/wiki/Framingham,_Massachusetts",
        "matchedText": "Framingham",
        "freebaseId": "/m/01m2n1",
        "relevanceScore": 0.0847079,
        "entityEnglishId": "Framingham, Massachusetts",
        "startingPos": 784,
        "endingPos": 794
      },
      {
        "id": 24,
        "matchingTokens": [
          161
        ],
        "entityId": "Sensitivity and specificity",
        "confidenceScore": 2.09099,
        "wikiLink": "http://en.wikipedia.org/wiki/Sensitivity_and_specificity",
        "matchedText": "specificity",
        "freebaseId": "/m/047vmjj",
        "relevanceScore": 0.589608,
        "entityEnglishId": "Sensitivity and specificity",
        "startingPos": 827,
        "endingPos": 838
      },
      {
        "id": 25,
        "matchingTokens": [
          173
        ],
        "entityId": "Risk",
        "freebaseTypes": [
          "/book/book_subject",
          "/media_common/quotation_subject"
        ],
        "confidenceScore": 1.07397,
        "wikiLink": "http://en.wikipedia.org/wiki/Risk",
        "matchedText": "risk",
        "freebaseId": "/m/06d5f",
        "relevanceScore": 0.295924,
        "entityEnglishId": "Risk",
        "startingPos": 903,
        "endingPos": 907
      },
      {
        "id": 26,
        "matchingTokens": [
          199
        ],
        "entityId": "Risk",
        "freebaseTypes": [
          "/book/book_subject",
          "/media_common/quotation_subject"
        ],
        "confidenceScore": 1.07397,
        "wikiLink": "http://en.wikipedia.org/wiki/Risk",
        "matchedText": "risk",
        "freebaseId": "/m/06d5f",
        "relevanceScore": 0.295924,
        "entityEnglishId": "Risk",
        "startingPos": 1033,
        "endingPos": 1037
      },
      {
        "id": 27,
        "matchingTokens": [
          201
        ],
        "entityId": "Sensitivity and specificity",
        "confidenceScore": 2.09099,
        "wikiLink": "http://en.wikipedia.org/wiki/Sensitivity_and_specificity",
        "matchedText": "specificity",
        "freebaseId": "/m/047vmjj",
        "relevanceScore": 0.589608,
        "entityEnglishId": "Sensitivity and specificity",
        "startingPos": 1039,
        "endingPos": 1050
      },
      {
        "id": 28,
        "type": [
          "Place",
          "PopulatedPlace",
          "Country"
        ],
        "matchingTokens": [
          205,
          206
        ],
        "entityId": "New Zealand",
        "freebaseTypes": [
          "/sports/sport_country",
          "/location/administrative_division",
          "/meteorology/cyclone_affected_area",
          "/tv/tv_location",
          "/business/employer",
          "/symbols/flag_referent",
          "/olympics/olympic_participating_country",
          "/sports/sports_team_location",
          "/location/statistical_region",
          "/fictional_universe/fictional_setting",
          "/location/location",
          "/military/military_combatant",
          "/biology/breed_origin",
          "/book/book_subject",
          "/organization/organization_founder",
          "/periodicals/newspaper_circulation_area",
          "/organization/organization_member",
          "/film/film_location",
          "/royalty/kingdom",
          "/organization/organization_scope",
          "/government/governmental_jurisdiction",
          "/location/dated_location",
          "/location/country",
          "/symbols/coat_of_arms_bearer",
          "/organization/organization_sector",
          "/food/beer_country_region"
        ],
        "confidenceScore": 2.99785,
        "wikiLink": "http://en.wikipedia.org/wiki/New_Zealand",
        "matchedText": "New Zealand",
        "freebaseId": "/m/0ctw_b",
        "relevanceScore": 0.0845075,
        "entityEnglishId": "New Zealand",
        "startingPos": 1057,
        "endingPos": 1068
      },
      {
        "id": 29,
        "matchingTokens": [
          210
        ],
        "entityId": "Sensitivity and specificity",
        "confidenceScore": 1.63722,
        "wikiLink": "http://en.wikipedia.org/wiki/Sensitivity_and_specificity",
        "matchedText": "sensitivity",
        "freebaseId": "/m/047vmjj",
        "relevanceScore": 0.492979,
        "entityEnglishId": "Sensitivity and specificity",
        "startingPos": 1082,
        "endingPos": 1093
      },
      {
        "id": 30,
        "matchingTokens": [
          214
        ],
        "entityId": "Sensitivity and specificity",
        "confidenceScore": 2.09099,
        "wikiLink": "http://en.wikipedia.org/wiki/Sensitivity_and_specificity",
        "matchedText": "specificity",
        "freebaseId": "/m/047vmjj",
        "relevanceScore": 0.589608,
        "entityEnglishId": "Sensitivity and specificity",
        "startingPos": 1105,
        "endingPos": 1116
      },
      {
        "id": 31,
        "matchingTokens": [
          227
        ],
        "entityId": "Risk",
        "freebaseTypes": [
          "/book/book_subject",
          "/media_common/quotation_subject"
        ],
        "confidenceScore": 1.34692,
        "wikiLink": "http://en.wikipedia.org/wiki/Risk",
        "matchedText": "risk",
        "freebaseId": "/m/06d5f",
        "relevanceScore": 0.295924,
        "entityEnglishId": "Risk",
        "startingPos": 1167,
        "endingPos": 1171
      },
      {
        "id": 32,
        "matchingTokens": [
          235
        ],
        "entityId": "Risk",
        "freebaseTypes": [
          "/book/book_subject",
          "/media_common/quotation_subject"
        ],
        "confidenceScore": 1.34692,
        "wikiLink": "http://en.wikipedia.org/wiki/Risk",
        "matchedText": "risk",
        "freebaseId": "/m/06d5f",
        "relevanceScore": 0.295924,
        "entityEnglishId": "Risk",
        "startingPos": 1195,
        "endingPos": 1199
      },
      {
        "id": 33,
        "matchingTokens": [
          237
        ],
        "entityId": "Sensitivity and specificity",
        "confidenceScore": 2.09099,
        "wikiLink": "http://en.wikipedia.org/wiki/Sensitivity_and_specificity",
        "matchedText": "specificity",
        "freebaseId": "/m/047vmjj",
        "relevanceScore": 0.589608,
        "entityEnglishId": "Sensitivity and specificity",
        "startingPos": 1201,
        "endingPos": 1212
      },
      {
        "id": 34,
        "type": [
          "Company"
        ],
        "matchingTokens": [
          243,
          244
        ],
        "entityId": "Joint Eu",
        "freebaseTypes": [
          "/organization/organization"
        ],
        "confidenceScore": 0.5,
        "wikiLink": "",
        "matchedText": "Joint Eu",
        "relevanceScore": 0,
        "entityEnglishId": "",
        "startingPos": 1238,
        "endingPos": 1246
      },
      {
        "id": 35,
        "matchingTokens": [
          250
        ],
        "entityId": "Sensitivity and specificity",
        "confidenceScore": 1.63722,
        "wikiLink": "http://en.wikipedia.org/wiki/Sensitivity_and_specificity",
        "matchedText": "sensitivity",
        "freebaseId": "/m/047vmjj",
        "relevanceScore": 0.492979,
        "entityEnglishId": "Sensitivity and specificity",
        "startingPos": 1269,
        "endingPos": 1280
      },
      {
        "id": 36,
        "matchingTokens": [
          254
        ],
        "entityId": "Risk",
        "freebaseTypes": [
          "/book/book_subject",
          "/media_common/quotation_subject"
        ],
        "confidenceScore": 0.968106,
        "wikiLink": "http://en.wikipedia.org/wiki/Risk",
        "matchedText": "risk",
        "freebaseId": "/m/06d5f",
        "relevanceScore": 0.295924,
        "entityEnglishId": "Risk",
        "startingPos": 1292,
        "endingPos": 1296
      },
      {
        "id": 37,
        "matchingTokens": [
          263
        ],
        "entityId": "Sensitivity and specificity",
        "confidenceScore": 2.09099,
        "wikiLink": "http://en.wikipedia.org/wiki/Sensitivity_and_specificity",
        "matchedText": "specificity",
        "freebaseId": "/m/047vmjj",
        "relevanceScore": 0.589608,
        "entityEnglishId": "Sensitivity and specificity",
        "startingPos": 1337,
        "endingPos": 1348
      },
      {
        "id": 38,
        "matchingTokens": [
          274
        ],
        "entityId": "Patient",
        "freebaseTypes": [
          "/fictional_universe/character_occupation"
        ],
        "confidenceScore": 1.2725,
        "wikiLink": "http://en.wikipedia.org/wiki/Patient",
        "matchedText": "patients",
        "freebaseId": "/m/028hfb",
        "relevanceScore": 0.0329545,
        "entityEnglishId": "Patient",
        "startingPos": 1390,
        "endingPos": 1398
      },
      {
        "id": 39,
        "matchingTokens": [
          282
        ],
        "entityId": "Risk",
        "freebaseTypes": [
          "/book/book_subject",
          "/media_common/quotation_subject"
        ],
        "confidenceScore": 0.968106,
        "wikiLink": "http://en.wikipedia.org/wiki/Risk",
        "matchedText": "risk",
        "freebaseId": "/m/06d5f",
        "relevanceScore": 0.295924,
        "entityEnglishId": "Risk",
        "startingPos": 1443,
        "endingPos": 1447
      }
    ],
    "relations": [
      {
        "id": 0,
        "wordPositions": [
          248
        ],
        "params": [
          {
            "relation": "SUBJECT",
            "wordPositions": [
              242,
              243,
              244,
              245,
              246,
              247
            ]
          },
          {
            "relation": "OBJECT",
            "wordPositions": [
              249,
              250,
              251,
              252,
              253,
              254,
              255,
              256,
              257,
              258,
              259,
              260,
              261,
              262,
              263,
              264,
              265,
              266
            ]
          }
        ]
      },
      {
        "id": 1,
        "wordPositions": [
          269
        ],
        "params": [
          {
            "relation": "SUBJECT",
            "wordPositions": [
              268
            ]
          },
          {
            "relation": "OBJECT",
            "wordPositions": [
              270,
              271,
              272,
              273,
              274,
              275,
              276,
              277,
              278,
              279,
              280,
              281,
              282,
              283,
              284,
              285,
              286
            ]
          }
        ]
      },
      {
        "id": 2,
        "wordPositions": [
          269,
          275,
          276,
          277,
          278,
          279
        ],
        "params": [
          {
            "relation": "SUBJECT",
            "wordPositions": [
              268,
              271,
              272,
              273,
              274
            ]
          },
          {
            "relation": "OBJECT",
            "wordPositions": [
              270,
              280,
              281,
              282,
              283,
              284,
              285,
              286
            ]
          }
        ]
      },
      {
        "id": 3,
        "wordPositions": [
          275,
          276,
          277,
          278,
          279
        ],
        "params": [
          {
            "relation": "SUBJECT",
            "wordPositions": [
              271,
              272,
              273,
              274
            ]
          },
          {
            "relation": "OBJECT",
            "wordPositions": [
              270,
              280,
              281,
              282,
              283,
              284,
              285,
              286
            ]
          }
        ]
      },
      {
        "id": 4,
        "wordPositions": [
          208,
          217
        ],
        "params": [
          {
            "relation": "SUBJECT",
            "wordPositions": [
              205,
              206,
              207
            ]
          },
          {
            "relation": "OBJECT",
            "wordPositions": [
              209,
              210,
              211,
              212,
              213,
              214,
              215,
              216,
              218,
              219,
              220,
              221,
              222,
              223,
              224,
              225,
              226,
              227,
              229,
              230,
              231,
              232,
              233,
              234,
              235,
              237,
              238,
              239,
              240
            ]
          }
        ]
      },
      {
        "id": 5,
        "wordPositions": [
          229,
          238,
          239
        ],
        "params": [
          {
            "relation": "SUBJECT",
            "wordPositions": [
              237
            ]
          },
          {
            "relation": "OBJECT",
            "wordPositions": [
              230,
              231,
              232,
              233,
              234,
              235,
              240
            ]
          }
        ]
      },
      {
        "id": 6,
        "wordPositions": [
          208,
          217,
          229,
          238,
          239
        ],
        "params": [
          {
            "relation": "SUBJECT",
            "wordPositions": [
              205,
              206,
              207,
              237
            ]
          },
          {
            "relation": "OBJECT",
            "wordPositions": [
              209,
              210,
              211,
              212,
              213,
              214,
              215,
              216,
              218,
              219,
              220,
              221,
              222,
              223,
              224,
              225,
              226,
              227,
              230,
              231,
              232,
              233,
              234,
              235,
              240
            ]
          }
        ]
      },
      {
        "id": 7,
        "wordPositions": [
          158,
          189
        ],
        "params": [
          {
            "relation": "SUBJECT",
            "wordPositions": [
              154,
              155,
              156,
              157
            ]
          },
          {
            "relation": "OBJECT",
            "wordPositions": [
              159,
              160,
              161,
              163,
              165,
              166,
              167,
              168,
              169,
              170,
              172,
              173,
              174,
              175,
              176,
              177,
              178,
              179,
              180,
              181,
              182,
              183,
              184,
              185,
              186,
              187,
              190,
              191,
              192,
              193,
              194,
              195,
              196,
              197,
              198,
              199,
              201,
              202
            ]
          }
        ]
      },
      {
        "id": 8,
        "wordPositions": [
          191,
          192
        ],
        "params": [
          {
            "relation": "SUBJECT",
            "wordPositions": [
              190
            ]
          },
          {
            "relation": "OBJECT",
            "wordPositions": [
              193,
              194,
              195,
              196,
              197,
              198,
              199,
              201,
              202
            ]
          }
        ]
      },
      {
        "id": 9,
        "wordPositions": [
          71,
          78,
          85
        ],
        "params": [
          {
            "relation": "SUBJECT",
            "wordPositions": [
              66,
              67,
              68,
              69,
              70
            ]
          },
          {
            "relation": "OBJECT",
            "wordPositions": [
              72,
              73,
              75,
              79,
              80,
              81,
              83,
              86,
              87,
              88,
              89,
              90,
              91,
              92,
              93,
              94,
              95,
              96,
              97,
              98,
              99,
              100,
              101,
              102,
              103,
              104,
              106,
              107,
              109,
              110
            ]
          }
        ]
      },
      {
        "id": 10,
        "wordPositions": [
          88,
          89,
          90
        ],
        "params": [
          {
            "relation": "SUBJECT",
            "wordPositions": [
              79,
              80,
              81,
              83,
              86,
              87
            ]
          },
          {
            "relation": "OBJECT",
            "wordPositions": [
              91,
              92,
              93,
              94,
              95,
              96,
              97,
              98,
              99,
              100,
              101,
              102,
              103,
              104,
              106,
              107,
              109,
              110
            ]
          }
        ]
      },
      {
        "id": 11,
        "wordPositions": [
          71,
          78,
          85,
          88,
          89,
          90
        ],
        "params": [
          {
            "relation": "SUBJECT",
            "wordPositions": [
              66,
              67,
              68,
              69,
              70,
              79,
              80,
              81,
              83,
              86,
              87
            ]
          },
          {
            "relation": "OBJECT",
            "wordPositions": [
              72,
              73,
              75,
              91,
              92,
              93,
              94,
              95,
              96,
              97,
              98,
              99,
              100,
              101,
              102,
              103,
              104,
              106,
              107,
              109,
              110
            ]
          }
        ]
      },
      {
        "id": 12,
        "wordPositions": [
          115,
          116,
          117,
          123,
          124,
          125,
          126,
          127,
          130,
          131
        ],
        "params": [
          {
            "relation": "SUBJECT",
            "wordPositions": [
              113,
              114
            ]
          },
          {
            "relation": "OBJECT",
            "wordPositions": [
              118,
              119,
              120,
              121,
              128,
              129,
              132,
              133,
              134,
              135,
              136,
              137,
              139,
              140,
              142,
              143,
              145,
              146,
              147,
              148,
              150,
              151
            ]
          }
        ]
      }
    ],
    "properties": [
      {
        "id": 0,
        "wordPositions": [
          249,
          250,
          251,
          253
        ],
        "propertyPositions": [
          252
        ]
      },
      {
        "id": 1,
        "wordPositions": [
          249,
          250,
          251,
          253
        ],
        "propertyPositions": [
          254,
          255
        ]
      },
      {
        "id": 2,
        "wordPositions": [
          263,
          264
        ],
        "propertyPositions": [
          256,
          257,
          258,
          259,
          260,
          261,
          262
        ]
      },
      {
        "id": 3,
        "wordPositions": [
          263,
          264
        ],
        "propertyPositions": [
          265,
          266
        ]
      },
      {
        "id": 4,
        "wordPositions": [
          9,
          11,
          12,
          13
        ],
        "propertyPositions": [
          10
        ]
      },
      {
        "id": 5,
        "wordPositions": [
          15,
          16
        ],
        "propertyPositions": [
          17
        ]
      },
      {
        "id": 6,
        "wordPositions": [
          9,
          11,
          12,
          13
        ],
        "propertyPositions": [
          14,
          15,
          16,
          17
        ]
      },
      {
        "id": 7,
        "wordPositions": [
          5,
          7,
          8
        ],
        "propertyPositions": [
          9,
          10,
          11,
          12,
          13,
          14,
          15,
          16,
          17
        ]
      },
      {
        "id": 8,
        "wordPositions": [
          21,
          22
        ],
        "propertyPositions": [
          20
        ]
      },
      {
        "id": 9,
        "wordPositions": [
          25,
          31
        ],
        "propertyPositions": [
          24
        ]
      },
      {
        "id": 10,
        "wordPositions": [
          214,
          215
        ],
        "propertyPositions": [
          216
        ]
      },
      {
        "id": 11,
        "wordPositions": [
          32,
          34,
          35,
          42
        ],
        "propertyPositions": [
          33
        ]
      },
      {
        "id": 12,
        "wordPositions": [
          32,
          34,
          35,
          42
        ],
        "propertyPositions": [
          36,
          38,
          39,
          40
        ]
      },
      {
        "id": 13,
        "wordPositions": [
          209,
          210,
          211
        ],
        "propertyPositions": [
          212,
          213,
          214,
          215,
          216
        ]
      },
      {
        "id": 14,
        "wordPositions": [
          44,
          46
        ],
        "propertyPositions": [
          45
        ]
      },
      {
        "id": 15,
        "wordPositions": [
          230,
          233,
          234
        ],
        "propertyPositions": [
          235
        ]
      },
      {
        "id": 16,
        "wordPositions": [
          50,
          55,
          56
        ],
        "propertyPositions": [
          51,
          52
        ]
      },
      {
        "id": 17,
        "wordPositions": [
          225,
          226
        ],
        "propertyPositions": [
          227
        ]
      },
      {
        "id": 18,
        "wordPositions": [
          50,
          55,
          56
        ],
        "propertyPositions": [
          53
        ]
      },
      {
        "id": 19,
        "wordPositions": [
          50,
          55,
          56
        ],
        "propertyPositions": [
          54
        ]
      },
      {
        "id": 20,
        "wordPositions": [
          57,
          59
        ],
        "propertyPositions": [
          58
        ]
      },
      {
        "id": 21,
        "wordPositions": [
          57,
          59
        ],
        "propertyPositions": [
          61,
          62,
          63
        ]
      },
      {
        "id": 22,
        "wordPositions": [
          50,
          55,
          56
        ],
        "propertyPositions": [
          57,
          58,
          59,
          61,
          62,
          63
        ]
      },
      {
        "id": 23,
        "wordPositions": [
          48,
          49
        ],
        "propertyPositions": [
          50,
          51,
          52,
          53,
          54,
          55,
          56,
          57,
          58,
          59,
          61,
          62,
          63
        ]
      },
      {
        "id": 24,
        "wordPositions": [
          32,
          34,
          35,
          42
        ],
        "propertyPositions": [
          44,
          45,
          46,
          48,
          49,
          50,
          51,
          52,
          53,
          54,
          55,
          56,
          57,
          58,
          59,
          61,
          62,
          63
        ]
      },
      {
        "id": 25,
        "wordPositions": [
          25,
          31
        ],
        "propertyPositions": [
          32,
          33,
          34,
          35,
          36,
          38,
          39,
          40,
          42,
          43,
          44,
          45,
          46,
          48,
          49,
          50,
          51,
          52,
          53,
          54,
          55,
          56,
          57,
          58,
          59,
          61,
          62,
          63
        ]
      },
      {
        "id": 26,
        "wordPositions": [
          154,
          155,
          157
        ],
        "propertyPositions": [
          156
        ]
      },
      {
        "id": 27,
        "wordPositions": [
          159,
          161,
          165
        ],
        "propertyPositions": [
          160
        ]
      },
      {
        "id": 28,
        "wordPositions": [
          159,
          161,
          165
        ],
        "propertyPositions": [
          163
        ]
      },
      {
        "id": 29,
        "wordPositions": [
          170
        ],
        "propertyPositions": [
          169
        ]
      },
      {
        "id": 30,
        "wordPositions": [
          166,
          167,
          168
        ],
        "propertyPositions": [
          169,
          170
        ]
      },
      {
        "id": 31,
        "wordPositions": [
          159,
          161,
          165
        ],
        "propertyPositions": [
          166,
          167,
          168,
          169,
          170
        ]
      },
      {
        "id": 32,
        "wordPositions": [
          173
        ],
        "propertyPositions": [
          172,
          174,
          175,
          176,
          177,
          178,
          179,
          180,
          181,
          182,
          183,
          184,
          185,
          186,
          187,
          190,
          191,
          192,
          193,
          194,
          195,
          196,
          197,
          198,
          199,
          201,
          202
        ]
      },
      {
        "id": 33,
        "wordPositions": [
          199
        ],
        "propertyPositions": [
          201,
          202
        ]
      },
      {
        "id": 34,
        "wordPositions": [
          193,
          194
        ],
        "propertyPositions": [
          195,
          196,
          197,
          198,
          199,
          201,
          202
        ]
      },
      {
        "id": 35,
        "wordPositions": [
          66,
          67,
          68,
          70
        ],
        "propertyPositions": [
          69
        ]
      },
      {
        "id": 36,
        "wordPositions": [
          73
        ],
        "propertyPositions": [
          72
        ]
      },
      {
        "id": 37,
        "wordPositions": [
          79,
          80,
          81
        ],
        "propertyPositions": [
          83
        ]
      },
      {
        "id": 38,
        "wordPositions": [
          91,
          93,
          94,
          95
        ],
        "propertyPositions": [
          92
        ]
      },
      {
        "id": 39,
        "wordPositions": [
          91,
          93,
          94,
          95
        ],
        "propertyPositions": [
          96,
          97,
          98,
          99,
          100,
          101,
          102,
          103,
          104
        ]
      },
      {
        "id": 40,
        "wordPositions": [
          114
        ],
        "propertyPositions": [
          113
        ]
      },
      {
        "id": 41,
        "wordPositions": [
          139
        ],
        "propertyPositions": [
          142,
          143
        ]
      },
      {
        "id": 42,
        "wordPositions": [
          139
        ],
        "propertyPositions": [
          146,
          147,
          148
        ]
      },
      {
        "id": 43,
        "wordPositions": [
          135,
          136
        ],
        "propertyPositions": [
          139,
          140,
          142,
          143,
          145,
          146,
          147,
          148,
          150,
          151
        ]
      },
      {
        "id": 44,
        "wordPositions": [
          135,
          136
        ],
        "propertyPositions": [
          137
        ]
      }
    ]
  },
  "time": 3.08,
  "ok": true
}